pyerrorschema/__init__.py
pyerrorschema/types.py
pyerrorschema/version.py
pyerrorschema/base/__init__.py
pyerrorschema/base/err_base.py
pyerrorschema/base/err_group.py
pyerrorschema/fastapi/__init__.py
pyerrorschema/fastapi/fastapi_base.py
pyerrorschema/fastapi/fastapi_group.py
pyerrorschema/fastapi/location.py
pyerrorschema/mappings/__init__.py
pyerrorschema/mappings/exceptions.py
pyerrorschema/mappings/mapper.py
pyerrorschema/utils/__init__.py
pyerrorschema/utils/class_utils.py
pyerrorschema/utils/decorators.py
pyerrorschema-2.1.0.dist-info/LICENSE.txt
pyerrorschema-2.1.0.dist-info/METADATA
pyerrorschema-2.1.0.dist-info/WHEEL
pyerrorschema-2.1.0.dist-info/top_level.txt
pyerrorschema-2.1.0.dist-info/RECORD
