Metadata-Version: 2.1
Name: pyerrorschema
Version: 2.1.0
Summary: Structured error handling framework for Python
Author-email: Elliot Su <sodinfeliz@google.com>
License: Copyright (c) 2024, Elliot Su.
Project-URL: Documentation, https://github.com/sodinfeliz/PyErrorSchema#readme
Project-URL: Issues, https://github.com/sodinfeliz/PyErrorSchema/issues
Project-URL: Source, https://github.com/sodinfeliz/PyErrorSchema
Classifier: License :: OSI Approved :: BSD License
Classifier: Programming Language :: Python :: 3
Classifier: Programming Language :: Python :: 3 :: Only
Classifier: Programming Language :: Python :: 3.8
Classifier: Programming Language :: Python :: 3.9
Classifier: Programming Language :: Python :: 3.10
Classifier: Programming Language :: Python :: 3.11
Classifier: Programming Language :: Python :: 3.12
Classifier: Operating System :: OS Independent
Classifier: Framework :: Pydantic :: 2
Requires-Python: >=3.8
License-File: LICENSE.txt
Requires-Dist: pydantic<3.0.0,>=2.6.4
Provides-Extra: dev
Requires-Dist: pytest>=8.3.4; extra == "dev"
Requires-Dist: pytest-cov>=4.1.0; extra == "dev"
Requires-Dist: ruff>=0.2.0; extra == "dev"
Requires-Dist: mypy>=1.8.0; extra == "dev"
Requires-Dist: build>=1.0.0; extra == "dev"
Requires-Dist: twine>=4.0.0; extra == "dev"
Requires-Dist: pre-commit>=3.5.0; extra == "dev"
